verysimplemodule/__init__.py
verysimplemodule/add.py
verysimplemodule/subtract.py
verysimplemodule/extras/__init__.py
verysimplemodule/extras/divide.py
verysimplemodule/extras/multiply.py
mercedesverysimplemodule-0.0.1.dist-info/METADATA
mercedesverysimplemodule-0.0.1.dist-info/WHEEL
mercedesverysimplemodule-0.0.1.dist-info/top_level.txt
mercedesverysimplemodule-0.0.1.dist-info/RECORD
